LICENSE
README.md
pyproject.toml
mobly/__init__.py
mobly/asserts.py
mobly/base_instrumentation_test.py
mobly/base_suite.py
mobly/base_test.py
mobly/config_parser.py
mobly/controller_manager.py
mobly/expects.py
mobly/keys.py
mobly/logger.py
mobly/records.py
mobly/runtime_test_info.py
mobly/signals.py
mobly/suite_runner.py
mobly/test_runner.py
mobly/utils.py
mobly.egg-info/PKG-INFO
mobly.egg-info/SOURCES.txt
mobly.egg-info/dependency_links.txt
mobly.egg-info/requires.txt
mobly.egg-info/top_level.txt
mobly/controllers/__init__.py
mobly/controllers/android_device.py
mobly/controllers/attenuator.py
mobly/controllers/iperf_server.py
mobly/controllers/sniffer.py
mobly/controllers/android_device_lib/__init__.py
mobly/controllers/android_device_lib/adb.py
mobly/controllers/android_device_lib/apk_utils.py
mobly/controllers/android_device_lib/callback_handler.py
mobly/controllers/android_device_lib/callback_handler_v2.py
mobly/controllers/android_device_lib/errors.py
mobly/controllers/android_device_lib/event_dispatcher.py
mobly/controllers/android_device_lib/fastboot.py
mobly/controllers/android_device_lib/jsonrpc_client_base.py
mobly/controllers/android_device_lib/jsonrpc_shell_base.py
mobly/controllers/android_device_lib/service_manager.py
mobly/controllers/android_device_lib/sl4a_client.py
mobly/controllers/android_device_lib/snippet_client.py
mobly/controllers/android_device_lib/snippet_client_v2.py
mobly/controllers/android_device_lib/snippet_event.py
mobly/controllers/android_device_lib/services/__init__.py
mobly/controllers/android_device_lib/services/base_service.py
mobly/controllers/android_device_lib/services/logcat.py
mobly/controllers/android_device_lib/services/sl4a_service.py
mobly/controllers/android_device_lib/services/snippet_management_service.py
mobly/controllers/attenuator_lib/__init__.py
mobly/controllers/attenuator_lib/minicircuits.py
mobly/controllers/attenuator_lib/telnet_scpi_client.py
mobly/controllers/sniffer_lib/__init__.py
mobly/controllers/sniffer_lib/local/__init__.py
mobly/controllers/sniffer_lib/local/local_base.py
mobly/controllers/sniffer_lib/local/tcpdump.py
